MANIFEST.in
README.rst
setup.py
django_view_timer/__init__.py
django_view_timer/logger.py
django_view_timer/profiler.py
django_view_timer/settings.py
django_view_timer/urls.py
django_view_timer.egg-info/PKG-INFO
django_view_timer.egg-info/SOURCES.txt
django_view_timer.egg-info/dependency_links.txt
django_view_timer.egg-info/not-zip-safe
django_view_timer.egg-info/requires.txt
django_view_timer.egg-info/top_level.txt