Metadata-Version: 1.1
Name: django-view-timer
Version: 0.2
Summary: Django View Timer
Home-page: https://github.com/aledista/django-view-timer
Author: Alessio Di Stasio
Author-email: aledista@gmail.com
License: BSD
Platform: UNKNOWN
Classifier: Development Status :: 4 - Beta
Classifier: Environment :: Web Environment
Classifier: Intended Audience :: Developers
Classifier: License :: OSI Approved :: BSD License
Classifier: Operating System :: OS Independent
Classifier: Programming Language :: Python
